Full_adder/design.vhd
library ieee;
use ieee.STD_logic_1164.ALL;

entity full_adder is
    port(
        a,b,c : in std_logic;
        sum ,carry : out std_logic
    );
end full_adder;

architecture dataflow of full_adder is
begin
    sum <= (a xor b) xor c;
    carry <= ((a xor b) and c) or (a and b);
end dataflow;

Full_adder/testbench.vhd
library ieee;
use ieee.STD_logic_1164.all;

entity full_adder_tb is
end entity;

architecture tb of full_adder_tb is
    component full_adder is
        port(
        a,b,c : in std_logic;
        sum ,carry : out std_logic
    );
    end component;

    signal a, b, c, sum, carry: std_logic;

begin 
    uut : full_adder port map(
    a => a , b => b , c => c , sum => sum , carry => carry
    );

    stim: process
    begin

        a <= '0';
        b <= '0';
        c <= '0';
        wait for 20 ns;

        a <= '0';
        b <= '0';
        c <= '1';
        wait for 20 ns;

        a <= '0';
        b <= '1';
        c <= '0';
        wait for 20 ns;

        a <= '0';
        b <= '1';
        c <= '1';
        wait for 20 ns;

        a <= '1';
        b <= '0';
        c <= '0';
        wait for 20 ns;

        a <= '1';
        b <= '1';
        c <= '0';
        wait for 20 ns;

        a <= '1';
        b <= '0';
        c <= '1';
        wait for 20 ns;

        a <= '1';
        b <= '1';
        c <= '1';
        wait for 20 ns;
    assert false report "Reached end of test";
    wait;

end process;

end tb;

Full_adder/full_adder.vcd
$date
  Wed Sep  8 23:36:53 2021
$end
$version
  GHDL v0
$end
$timescale
  1 fs
$end
$scope module standard $end
$upscope $end
$scope module std_logic_1164 $end
$upscope $end
$scope module full_adder_tb $end
$var reg 1 ! a $end
$var reg 1 " b $end
$var reg 1 # c $end
$var reg 1 $ sum $end
$var reg 1 % carry $end
$scope module uut $end
$var reg 1 & a $end
$var reg 1 ' b $end
$var reg 1 ( c $end
$var reg 1 ) sum $end
$var reg 1 * carry $end
$upscope $end
$upscope $end
$enddefinitions $end
#0
0!
0"
0#
0$
0%
0&
0'
0(
0)
0*
#20000000
1#
1$
1(
1)
#40000000
1"
0#
1'
0(
#60000000
1#
0$
1%
1(
0)
1*
#80000000
1!
0"
0#
1$
0%
1&
0'
0(
1)
0*
#100000000
1"
0$
1%
1'
0)
1*
#120000000
0"
1#
0'
1(
#140000000
1"
1$
1'
1)
